simple_package/__init__.py
simple_package/main.py
pardhu_simple_package-0.1.1.dist-info/METADATA
pardhu_simple_package-0.1.1.dist-info/WHEEL
pardhu_simple_package-0.1.1.dist-info/top_level.txt
pardhu_simple_package-0.1.1.dist-info/RECORD
