Metadata-Version: 2.1
Name: pardhu-simple-package
Version: 0.1.1
Summary: A simple package
Author: Pardhu
Classifier: Programming Language :: Python :: 3
Classifier: License :: OSI Approved :: MIT License
Classifier: Operating System :: OS Independent
Requires-Python: >=3.6
Requires-Dist: jwt >=1.3.1
Requires-Dist: requests >=2.31.0
Requires-Dist: urllib3 >=2.0.7
